[{"Delantero":{"DatosPersonaje":{"Nombre":"Carlos Tevez","Apodo":"El Apache","FechaNacimiento":"1984-02-05T00:00:00","Edad":39},"CaracteristicasPersonaje":{"Control":8,"Marcaje":1,"Tiro":6,"Nivel":1,"Salud":0,"Intercepciones":2}},"Mediocampo":{"DatosPersonaje":{"Nombre":"Christian Eriksen","Apodo":"El Genio","FechaNacimiento":"1992-02-14T00:00:00","Edad":31},"CaracteristicasPersonaje":{"Control":2,"Marcaje":7,"Tiro":7,"Nivel":1,"Salud":0,"Intercepciones":5}},"DefensaOArquero":{"DatosPersonaje":{"Nombre":"Ederson Moraes","Apodo":"El Pulpo","FechaNacimiento":"1993-08-17T00:00:00","Edad":29},"CaracteristicasPersonaje":{"Control":2,"Marcaje":9,"Tiro":2,"Nivel":1,"Salud":0,"Intercepciones":5}},"Goles":0,"NombreEquipo":"Fenerbahce"},{"Delantero":{"DatosPersonaje":{"Nombre":"Hugo S\u00E1nchez","Apodo":"La Cobra","FechaNacimiento":"1986-02-10T00:00:00","Edad":37},"CaracteristicasPersonaje":{"Control":8,"Marcaje":4,"Tiro":5,"Nivel":1,"Salud":0,"Intercepciones":2}},"Mediocampo":{"DatosPersonaje":{"Nombre":"Kevin De Bruyne","Apodo":"El Cerebro","FechaNacimiento":"1991-06-28T00:00:00","Edad":31},"CaracteristicasPersonaje":{"Control":8,"Marcaje":4,"Tiro":8,"Nivel":1,"Salud":0,"Intercepciones":8}},"DefensaOArquero":{"DatosPersonaje":{"Nombre":"Raphael Varane","Apodo":"El Francotirador","FechaNacimiento":"1993-04-25T00:00:00","Edad":30},"CaracteristicasPersonaje":{"Control":3,"Marcaje":8,"Tiro":1,"Nivel":1,"Salud":0,"Intercepciones":6}},"Goles":0,"NombreEquipo":"Chelsea"},{"Delantero":{"DatosPersonaje":{"Nombre":"Hugo S\u00E1nchez","Apodo":"La Cobra","FechaNacimiento":"1986-02-10T00:00:00","Edad":37},"CaracteristicasPersonaje":{"Control":8,"Marcaje":3,"Tiro":8,"Nivel":1,"Salud":0,"Intercepciones":4}},"Mediocampo":{"DatosPersonaje":{"Nombre":"Luka Modric","Apodo":"El Mago","FechaNacimiento":"1985-09-09T00:00:00","Edad":37},"CaracteristicasPersonaje":{"Control":2,"Marcaje":3,"Tiro":2,"Nivel":1,"Salud":0,"Intercepciones":2}},"DefensaOArquero":{"DatosPersonaje":{"Nombre":"Kalidou Koulibaly","Apodo":"El Le\u00F3n de Senegal","FechaNacimiento":"1991-06-20T00:00:00","Edad":32},"CaracteristicasPersonaje":{"Control":3,"Marcaje":8,"Tiro":4,"Nivel":1,"Salud":0,"Intercepciones":5}},"Goles":0,"NombreEquipo":"Barcelona"},{"Delantero":{"DatosPersonaje":{"Nombre":"Christian Vieri","Apodo":"El Puma","FechaNacimiento":"1972-08-08T00:00:00","Edad":50},"CaracteristicasPersonaje":{"Control":7,"Marcaje":3,"Tiro":9,"Nivel":1,"Salud":0,"Intercepciones":3}},"Mediocampo":{"DatosPersonaje":{"Nombre":"Luka Modric","Apodo":"El Mago","FechaNacimiento":"1985-09-09T00:00:00","Edad":37},"CaracteristicasPersonaje":{"Control":2,"Marcaje":4,"Tiro":9,"Nivel":1,"Salud":0,"Intercepciones":5}},"DefensaOArquero":{"DatosPersonaje":{"Nombre":"Trent Alexander-Arnold","Apodo":"El Cohete","FechaNacimiento":"1998-10-07T00:00:00","Edad":24},"CaracteristicasPersonaje":{"Control":4,"Marcaje":9,"Tiro":3,"Nivel":1,"Salud":0,"Intercepciones":6}},"Goles":0,"NombreEquipo":"Anderlecht"},{"Delantero":{"DatosPersonaje":{"Nombre":"Diego Maradona","Apodo":"El Diego","FechaNacimiento":"1960-10-30T00:00:00","Edad":62},"CaracteristicasPersonaje":{"Control":7,"Marcaje":3,"Tiro":9,"Nivel":1,"Salud":0,"Intercepciones":3}},"Mediocampo":{"DatosPersonaje":{"Nombre":"Christian Eriksen","Apodo":"El Genio","FechaNacimiento":"1992-02-14T00:00:00","Edad":31},"CaracteristicasPersonaje":{"Control":8,"Marcaje":8,"Tiro":9,"Nivel":1,"Salud":0,"Intercepciones":5}},"DefensaOArquero":{"DatosPersonaje":{"Nombre":"Trent Alexander-Arnold","Apodo":"El Cohete","FechaNacimiento":"1998-10-07T00:00:00","Edad":24},"CaracteristicasPersonaje":{"Control":3,"Marcaje":8,"Tiro":1,"Nivel":1,"Salud":0,"Intercepciones":8}},"Goles":0,"NombreEquipo":"Grasshopper Club Zurich"},{"Delantero":{"DatosPersonaje":{"Nombre":"Edinson Cavani","Apodo":"El Matador","FechaNacimiento":"1987-02-14T00:00:00","Edad":36},"CaracteristicasPersonaje":{"Control":9,"Marcaje":4,"Tiro":7,"Nivel":1,"Salud":0,"Intercepciones":2}},"Mediocampo":{"DatosPersonaje":{"Nombre":"Xavi Hern\u00E1ndez","Apodo":"El Maestro","FechaNacimiento":"1980-01-25T00:00:00","Edad":43},"CaracteristicasPersonaje":{"Control":5,"Marcaje":6,"Tiro":2,"Nivel":1,"Salud":0,"Intercepciones":7}},"DefensaOArquero":{"DatosPersonaje":{"Nombre":"Thibaut Courtois","Apodo":"La Muralla","FechaNacimiento":"1992-05-11T00:00:00","Edad":31},"CaracteristicasPersonaje":{"Control":2,"Marcaje":9,"Tiro":2,"Nivel":1,"Salud":0,"Intercepciones":7}},"Goles":0,"NombreEquipo":"Roma"},{"Delantero":{"DatosPersonaje":{"Nombre":"Ronaldo Naz\u00E1rio","Apodo":"El Fen\u00F3meno","FechaNacimiento":"1976-09-22T00:00:00","Edad":46},"CaracteristicasPersonaje":{"Control":8,"Marcaje":1,"Tiro":5,"Nivel":1,"Salud":0,"Intercepciones":1}},"Mediocampo":{"DatosPersonaje":{"Nombre":"Andr\u00E9s Iniesta","Apodo":"El Cerebro","FechaNacimiento":"1984-05-11T00:00:00","Edad":39},"CaracteristicasPersonaje":{"Control":1,"Marcaje":1,"Tiro":2,"Nivel":1,"Salud":0,"Intercepciones":9}},"DefensaOArquero":{"DatosPersonaje":{"Nombre":"Ederson Moraes","Apodo":"El Pulpo","FechaNacimiento":"1993-08-17T00:00:00","Edad":29},"CaracteristicasPersonaje":{"Control":1,"Marcaje":8,"Tiro":2,"Nivel":1,"Salud":0,"Intercepciones":8}},"Goles":0,"NombreEquipo":"Celtic"},{"Delantero":{"DatosPersonaje":{"Nombre":"Juan Rom\u00E1n Riquelme","Apodo":"El Tanque","FechaNacimiento":"1958-02-11T00:00:00","Edad":65},"CaracteristicasPersonaje":{"Control":9,"Marcaje":1,"Tiro":9,"Nivel":1,"Salud":0,"Intercepciones":2}},"Mediocampo":{"DatosPersonaje":{"Nombre":"Kevin De Bruyne","Apodo":"El Cerebro","FechaNacimiento":"1991-06-28T00:00:00","Edad":31},"CaracteristicasPersonaje":{"Control":4,"Marcaje":2,"Tiro":8,"Nivel":1,"Salud":0,"Intercepciones":7}},"DefensaOArquero":{"DatosPersonaje":{"Nombre":"Ederson Moraes","Apodo":"El Pulpo","FechaNacimiento":"1993-08-17T00:00:00","Edad":29},"CaracteristicasPersonaje":{"Control":2,"Marcaje":6,"Tiro":2,"Nivel":1,"Salud":0,"Intercepciones":5}},"Goles":0,"NombreEquipo":"Paris Saint-Germain"},{"Delantero":{"DatosPersonaje":{"Nombre":"Christian Vieri","Apodo":"El Puma","FechaNacimiento":"1972-08-08T00:00:00","Edad":50},"CaracteristicasPersonaje":{"Control":7,"Marcaje":2,"Tiro":8,"Nivel":1,"Salud":0,"Intercepciones":3}},"Mediocampo":{"DatosPersonaje":{"Nombre":"Andr\u00E9s Iniesta","Apodo":"El Cerebro","FechaNacimiento":"1984-05-11T00:00:00","Edad":39},"CaracteristicasPersonaje":{"Control":3,"Marcaje":6,"Tiro":3,"Nivel":1,"Salud":0,"Intercepciones":7}},"DefensaOArquero":{"DatosPersonaje":{"Nombre":"Ederson Moraes","Apodo":"El Pulpo","FechaNacimiento":"1993-08-17T00:00:00","Edad":29},"CaracteristicasPersonaje":{"Control":1,"Marcaje":8,"Tiro":4,"Nivel":1,"Salud":0,"Intercepciones":7}},"Goles":0,"NombreEquipo":"Lyon"},{"Delantero":{"DatosPersonaje":{"Nombre":"Javier Hern\u00E1ndez","Apodo":"Il Bambino d\u0027Oro","FechaNacimiento":"1935-07-19T00:00:00","Edad":87},"CaracteristicasPersonaje":{"Control":6,"Marcaje":3,"Tiro":6,"Nivel":1,"Salud":0,"Intercepciones":4}},"Mediocampo":{"DatosPersonaje":{"Nombre":"Xavi Hern\u00E1ndez","Apodo":"El Maestro","FechaNacimiento":"1980-01-25T00:00:00","Edad":43},"CaracteristicasPersonaje":{"Control":4,"Marcaje":2,"Tiro":6,"Nivel":1,"Salud":0,"Intercepciones":4}},"DefensaOArquero":{"DatosPersonaje":{"Nombre":"Jan Oblak","Apodo":"El Muro","FechaNacimiento":"1993-01-07T00:00:00","Edad":30},"CaracteristicasPersonaje":{"Control":3,"Marcaje":9,"Tiro":2,"Nivel":1,"Salud":0,"Intercepciones":6}},"Goles":0,"NombreEquipo":"Cruzeiro"}]
